gimmecert/__init__.py
gimmecert/cli.py
gimmecert/commands.py
gimmecert/crypto.py
gimmecert/decorators.py
gimmecert/storage.py
gimmecert/utils.py
gimmecert-1.0.0.dist-info/LICENSE-CC-BY-SA-3.0-Unported
gimmecert-1.0.0.dist-info/LICENSE-GPLv3
gimmecert-1.0.0.dist-info/METADATA
gimmecert-1.0.0.dist-info/WHEEL
gimmecert-1.0.0.dist-info/entry_points.txt
gimmecert-1.0.0.dist-info/top_level.txt
gimmecert-1.0.0.dist-info/RECORD
