Metadata-Version: 2.1
Name: gimmecert
Version: 1.0.0
Summary: A simple tool for quickly issuing server and client certificates.
Home-page: http://projects.majic.rs/gimmecert
Author: Branko Majic
Author-email: branko@majic.rs
License: GPLv3+
Platform: UNKNOWN
Classifier: Development Status :: 5 - Production/Stable
Classifier: Environment :: Console
Classifier: Intended Audience :: Developers
Classifier: Intended Audience :: System Administrators
Classifier: License :: OSI Approved :: GNU General Public License v3 or later (GPLv3+)
Classifier: Operating System :: OS Independent
Classifier: Programming Language :: Python :: 3.8
Classifier: Programming Language :: Python :: 3.9
Classifier: Programming Language :: Python :: 3.10
Classifier: Programming Language :: Python :: 3.11
Classifier: Programming Language :: Python :: 3.12
Classifier: Topic :: Internet :: WWW/HTTP
Classifier: Topic :: Internet :: WWW/HTTP :: Site Management
Classifier: Topic :: Security
Classifier: Topic :: Software Development :: Testing
Classifier: Topic :: Utilities
Requires-Python: >=3.8,<3.13
Requires-Dist: cryptography (<42.1,>=42.0)
Requires-Dist: python-dateutil (<2.9,>=2.8)
Provides-Extra: devel
Requires-Dist: sphinx (<7.2,>=7.1) ; extra == 'devel'
Requires-Dist: time-machine (<2.14,>=2.13) ; extra == 'devel'
Requires-Dist: pytest (<8.1,>=8.0) ; extra == 'devel'
Requires-Dist: pytest-cov (<4.2,>=4.1) ; extra == 'devel'
Requires-Dist: tox (<4.14,>=4.13) ; extra == 'devel'
Requires-Dist: pexpect (<4.10,>=4.9) ; extra == 'devel'
Requires-Dist: flake8 (<7.1,>=7.0) ; extra == 'devel'
Requires-Dist: twine ; extra == 'devel'
Provides-Extra: doc
Requires-Dist: sphinx (<7.2,>=7.1) ; extra == 'doc'
Provides-Extra: test
Requires-Dist: time-machine (<2.14,>=2.13) ; extra == 'test'
Requires-Dist: pytest (<8.1,>=8.0) ; extra == 'test'
Requires-Dist: pytest-cov (<4.2,>=4.1) ; extra == 'test'
Requires-Dist: tox (<4.14,>=4.13) ; extra == 'test'
Requires-Dist: pexpect (<4.10,>=4.9) ; extra == 'test'
Provides-Extra: testlint
Requires-Dist: flake8 (<7.1,>=7.0) ; extra == 'testlint'
